{
  "name": "azureblob-index",
  "fields": [
    {
      "name": "content",
      "type": "Edm.String",
      "facetable": false,
      "filterable": false,
      "key": false,
      "retrievable": false,
      "searchable": true,
      "sortable": false,
      "analyzer": "standard.lucene",
      "indexAnalyzer": null,
      "searchAnalyzer": null,
      "synonymMaps": [],
      "fields": []
    },
    {
      "name": "metadata_storage_path",
      "type": "Edm.String",
      "facetable": false,
      "filterable": false,
      "key": false,
      "retrievable": true,
      "searchable": false,
      "sortable": false,
      "analyzer": null,
      "indexAnalyzer": null,
      "searchAnalyzer": null,
      "synonymMaps": [],
      "fields": []
    },
    {
      "name": "metadata_content_type",
      "type": "Edm.String",
      "facetable": false,
      "filterable": false,
      "key": false,
      "retrievable": false,
      "searchable": false,
      "sortable": false,
      "analyzer": null,
      "indexAnalyzer": null,
      "searchAnalyzer": null,
      "synonymMaps": [],
      "fields": []
    },
    {
      "name": "metadata_language",
      "type": "Edm.String",
      "facetable": false,
      "filterable": false,
      "key": false,
      "retrievable": false,
      "searchable": false,
      "sortable": false,
      "analyzer": null,
      "indexAnalyzer": null,
      "searchAnalyzer": null,
      "synonymMaps": [],
      "fields": []
    },
    {
      "name": "created",
      "type": "Edm.String",
      "facetable": false,
      "filterable": false,
      "key": false,
      "retrievable": true,
      "searchable": false,
      "sortable": true,
      "analyzer": null,
      "indexAnalyzer": null,
      "searchAnalyzer": null,
      "synonymMaps": [],
      "fields": []
    },
    {
      "name": "release_state",
      "type": "Edm.String",
      "facetable": false,
      "filterable": true,
      "key": false,
      "retrievable": true,
      "searchable": false,
      "sortable": false,
      "analyzer": null,
      "indexAnalyzer": null,
      "searchAnalyzer": null,
      "synonymMaps": [],
      "fields": []
    },
    {
      "name": "keywords",
      "type": "Edm.String",
      "facetable": false,
      "filterable": false,
      "key": false,
      "retrievable": true,
      "searchable": true,
      "sortable": false,
      "analyzer": "standard.lucene",
      "indexAnalyzer": null,
      "searchAnalyzer": null,
      "synonymMaps": [],
      "fields": []
    },
    {
      "name": "title",
      "type": "Edm.String",
      "facetable": false,
      "filterable": false,
      "key": false,
      "retrievable": true,
      "searchable": true,
      "sortable": false,
      "analyzer": "standard.lucene",
      "indexAnalyzer": null,
      "searchAnalyzer": null,
      "synonymMaps": [],
      "fields": []
    },
    {
      "name": "file_name",
      "type": "Edm.String",
      "facetable": false,
      "filterable": false,
      "key": false,
      "retrievable": true,
      "searchable": true,
      "sortable": false,
      "analyzer": "standard.lucene",
      "indexAnalyzer": null,
      "searchAnalyzer": null,
      "synonymMaps": [],
      "fields": []
    },
    {
      "name": "metadata_storage_content_type",
      "type": "Edm.String",
      "facetable": false,
      "filterable": false,
      "key": false,
      "retrievable": false,
      "searchable": false,
      "sortable": false,
      "analyzer": null,
      "indexAnalyzer": null,
      "searchAnalyzer": null,
      "synonymMaps": [],
      "fields": []
    },
    {
      "name": "metadata_storage_size",
      "type": "Edm.Int64",
      "facetable": false,
      "filterable": false,
      "retrievable": true,
      "sortable": false,
      "analyzer": null,
      "indexAnalyzer": null,
      "searchAnalyzer": null,
      "synonymMaps": [],
      "fields": []
    },
    {
      "name": "metadata_storage_last_modified",
      "type": "Edm.DateTimeOffset",
      "facetable": false,
      "filterable": false,
      "retrievable": false,
      "sortable": false,
      "analyzer": null,
      "indexAnalyzer": null,
      "searchAnalyzer": null,
      "synonymMaps": [],
      "fields": []
    },
    {
      "name": "metadata_storage_content_md5",
      "type": "Edm.String",
      "facetable": false,
      "filterable": false,
      "key": false,
      "retrievable": false,
      "searchable": false,
      "sortable": false,
      "analyzer": null,
      "indexAnalyzer": null,
      "searchAnalyzer": null,
      "synonymMaps": [],
      "fields": []
    },
    {
      "name": "metadata_storage_name",
      "type": "Edm.String",
      "facetable": false,
      "filterable": false,
      "key": true,
      "retrievable": true,
      "searchable": false,
      "sortable": false,
      "analyzer": null,
      "indexAnalyzer": null,
      "searchAnalyzer": null,
      "synonymMaps": [],
      "fields": []
    },
    {
      "name": "doc_type",
      "type": "Edm.String",
      "facetable": false,
      "filterable": true,
      "key": false,
      "retrievable": true,
      "searchable": false,
      "sortable": false,
      "analyzer": null,
      "indexAnalyzer": null,
      "searchAnalyzer": null,
      "synonymMaps": [],
      "fields": []
    },
    {
      "name": "suggestions",
      "type": "Collection(Edm.String)",
      "facetable": false,
      "filterable": true,
      "retrievable": true,
      "searchable": false,
      "analyzer": null,
      "indexAnalyzer": null,
      "searchAnalyzer": null,
      "synonymMaps": [],
      "fields": []
    }
  ],
  "suggesters": [
    {
      "name": "azure-suggester",
      "searchMode": "analyzingInfixMatching",
      "sourceFields": ["suggestions", "title"]
    }
  ],
  "scoringProfiles": [
    {
      "name": "preferKeywords",
      "text": {
        "weights": {
          "keywords": 3
        }
      }
    }
  ],
  "defaultScoringProfile": "",
  "corsOptions": {
    "allowedOrigins": ["*"],
    "maxAgeInSeconds": 300
  },
  "analyzers": [],
  "charFilters": [],
  "tokenFilters": [],
  "tokenizers": [],
  "@odata.etag": "\"0x8D77267697666D4\""
}
